{
    "Mail": {
        "next": [
            "MailEnd"
        ],
        "interrupt": [
            "WuZi",
            "AllClaim",
            "GoMail"
        ]
    },
    "GoMail": {
        "recognition": "OCR",
        "expected": "邮件",
        "roi": [
            0,
            366,
            238,
            329
        ],
        "action": "Click",
        "target": true
    },
    "AllClaim": {
        "recognition": "OCR",
        "expected": "全部领取",
        "roi": [
            25,
            621,
            391,
            98
        ],
        "action": "Click",
        "target": true
    },
    "MailEnd": {
        "recognition": "OCR",
        "expected": [
            "没有可领取的附件"
        ],
        "next": "Home"
    }
}